miniworlds/__init__.py
miniworlds/conf.py
miniworlds/py.typed
miniworlds/actors/__init__.py
miniworlds/actors/actor.py
miniworlds/actors/actor_base.py
miniworlds/actors/parent_actor.py
miniworlds/actors/sensors/__init__.py
miniworlds/actors/sensors/circle_sensor.py
miniworlds/actors/sensors/sensor_actor.py
miniworlds/actors/sensors/sensor_base.py
miniworlds/actors/shapes/__init__.py
miniworlds/actors/shapes/shape_costume.py
miniworlds/actors/shapes/shapes.py
miniworlds/actors/texts/__init__.py
miniworlds/actors/texts/number.py
miniworlds/actors/texts/text.py
miniworlds/actors/texts/text_costume.py
miniworlds/actors/texts/text_transformation_manager.py
miniworlds/actors/texts/textbox.py
miniworlds/actors/widgets/__init__.py
miniworlds/actors/widgets/button.py
miniworlds/actors/widgets/container_widget.py
miniworlds/actors/widgets/counter.py
miniworlds/actors/widgets/fps.py
miniworlds/actors/widgets/input.py
miniworlds/actors/widgets/label.py
miniworlds/actors/widgets/load.py
miniworlds/actors/widgets/pagination.py
miniworlds/actors/widgets/save.py
miniworlds/actors/widgets/single_widget.py
miniworlds/actors/widgets/time.py
miniworlds/actors/widgets/widget_base.py
miniworlds/actors/widgets/widget_costume.py
miniworlds/actors/widgets/widget_parts.py
miniworlds/actors/widgets/yesno.py
miniworlds/appearances/__init__.py
miniworlds/appearances/appearance.py
miniworlds/appearances/appearances_manager.py
miniworlds/appearances/background.py
miniworlds/appearances/backgrounds_manager.py
miniworlds/appearances/costume.py
miniworlds/appearances/costumes_manager.py
miniworlds/appearances/managers/__init__.py
miniworlds/appearances/managers/font_manager.py
miniworlds/appearances/managers/image_background_manager.py
miniworlds/appearances/managers/image_manager.py
miniworlds/appearances/managers/transformations_background_manager.py
miniworlds/appearances/managers/transformations_costume_manager.py
miniworlds/appearances/managers/transformations_manager.py
miniworlds-3.1.0.1.dist-info/licenses/LICENSE.txt
miniworlds-3.1.0.1.dist-info/METADATA
miniworlds-3.1.0.1.dist-info/WHEEL
miniworlds-3.1.0.1.dist-info/top_level.txt
miniworlds-3.1.0.1.dist-info/RECORD
