Metadata-Version: 2.4
Name: miniworlds
Version: 3.1.0.1
Summary: Create 2D worlds and Games
Home-page: https://github.com/asbl/miniworlds
Download-URL: https://github.com/asbl/miniworlds
Author: Andreas Siebel
Author-email: andreas.siebel@it-teaching.de
License: OSI Approved :: MIT License
Keywords: games,education,mini-worlds,pygame
Classifier: License :: OSI Approved :: MIT License
Classifier: Programming Language :: Python
Classifier: Development Status :: 4 - Beta
Classifier: Intended Audience :: Education
Classifier: Topic :: Education
License-File: LICENSE.txt
Requires-Dist: pygame-ce
Requires-Dist: numpy
Dynamic: author
Dynamic: author-email
Dynamic: classifier
Dynamic: description
Dynamic: description-content-type
Dynamic: download-url
Dynamic: home-page
Dynamic: keywords
Dynamic: license
Dynamic: license-file
Dynamic: requires-dist
Dynamic: summary
